LICENSE
MANIFEST.in
README.md
setup.cfg
setup.py
django_mp_sms_templates.egg-info/PKG-INFO
django_mp_sms_templates.egg-info/SOURCES.txt
django_mp_sms_templates.egg-info/dependency_links.txt
django_mp_sms_templates.egg-info/top_level.txt
sms_templates/__init__.py
sms_templates/admin.py
sms_templates/exceptions.py
sms_templates/forms.py
sms_templates/lib.py
sms_templates/models.py
sms_templates/translation.py
sms_templates/locale/en/LC_MESSAGES/django.mo
sms_templates/locale/en/LC_MESSAGES/django.po
sms_templates/locale/ru/LC_MESSAGES/django.mo
sms_templates/locale/ru/LC_MESSAGES/django.po
sms_templates/locale/uk/LC_MESSAGES/django.mo
sms_templates/locale/uk/LC_MESSAGES/django.po
sms_templates/migrations/0001_initial.py
sms_templates/migrations/__init__.py
sms_templates/templates/sms_templates/list_item_actions.html
sms_templates/templates/sms_templates/send_sms.html