Metadata-Version: 1.1
Name: django-mp-sms-templates
Version: 1.3
Summary: SMS templates app
Home-page: https://github.com/pmaigutyak/mp-sms-templates
Author: Paul Maigutyak
Author-email: pmaigutyak@gmail.com
License: MIT
Download-URL: https://github.com/pmaigutyak/mp-sms-templates/archive/1.3.tar.gz
Platform: UNKNOWN
